[{"Plan": {"Node Type": "Limit", "Parallel Aware": false, "Async Capable": false, "Startup Cost": 444795.73, "Total Cost": 444795.98, "Plan Rows": 100, "Plan Width": 36, "Actual Startup Time": 866.758, "Actual Total Time": 866.857, "Actual Rows": 100, "Actual Loops": 1, "Plans": [{"Node Type": "Limit", "Parent Relationship": "InitPlan", "Subplan Name": "CTE top100_popular_forums", "Parallel Aware": false, "Async Capable": false, "Startup Cost": 18293.2, "Total Cost": 18304.86, "Plan Rows": 100, "Plan Width": 24, "Actual Startup Time": 81.46, "Actual Total Time": 81.597, "Actual Rows": 100, "Actual Loops": 1, "Plans": [{"Node Type": "Gather Merge", "Parent Relationship": "Outer", "Parallel Aware": false, "Async Capable": false, "Startup Cost": 18293.2, "Total Cost": 79334.42, "Plan Rows": 523174, "Plan Width": 24, "Actual Startup Time": 81.439, "Actual Total Time": 81.567, "Actual Rows": 100, "Actual Loops": 1, "Workers Planned": 2, "Workers Launched": 2, "Plans": [{"Node Type": "Sort", "Parent Relationship": "Outer", "Parallel Aware": false, "Async Capable": false, "Startup Cost": 17293.17, "Total Cost": 17947.14, "Plan Rows": 261587, "Plan Width": 24, "Actual Startup Time": 62.17, "Actual Total Time": 62.177, "Actual Rows": 88, "Actual Loops": 3, "Sort Key": ["top100popularforumsq04.maxnumberofmembers DESC", "top100popularforumsq04.id"], "Sort Method": "top-N heapsort", "Sort Space Used": 38, "Sort Space Type": "Memory", "Workers": [{"Worker Number": 0, "Sort Method": "top-N heapsort", "Sort Space Used": 38, "Sort Space Type": "Memory"}, {"Worker Number": 1, "Sort Method": "top-N heapsort", "Sort Space Used": 38, "Sort Space Type": "Memory"}], "Plans": [{"Node Type": "Seq Scan", "Parent Relationship": "Outer", "Parallel Aware": true, "Async Capable": false, "Relation Name": "top100popularforumsq04", "Alias": "top100popularforumsq04", "Startup Cost": 0.0, "Total Cost": 7295.51, "Plan Rows": 261587, "Plan Width": 24, "Actual Startup Time": 2.394, "Actual Total Time": 42.62, "Actual Rows": 209417, "Actual Loops": 3, "Filter": "(creationdate > '2010-01-26'::date)", "Rows Removed by Filter": 599, "Workers": []}]}]}]}, {"Node Type": "Sort", "Parent Relationship": "Outer", "Parallel Aware": false, "Async Capable": false, "Startup Cost": 426490.87, "Total Cost": 426576.15, "Plan Rows": 34113, "Plan Width": 36, "Actual Startup Time": 844.866, "Actual Total Time": 844.877, "Actual Rows": 100, "Actual Loops": 1, "Sort Key": ["(count(message.messageid)) DESC", "au.id"], "Sort Method": "top-N heapsort", "Sort Space Used": 38, "Sort Space Type": "Memory", "Plans": [{"Node Type": "Aggregate", "Strategy": "Sorted", "Partial Mode": "Simple", "Parent Relationship": "Outer", "Parallel Aware": false, "Async Capable": false, "Startup Cost": 424590.12, "Total Cost": 425187.09, "Plan Rows": 34113, "Plan Width": 36, "Actual Startup Time": 811.717, "Actual Total Time": 842.323, "Actual Rows": 13215, "Actual Loops": 1, "Group Key": ["au.id"], "Plans": [{"Node Type": "Sort", "Parent Relationship": "Outer", "Parallel Aware": false, "Async Capable": false, "Startup Cost": 424590.12, "Total Cost": 424675.4, "Plan Rows": 34113, "Plan Width": 36, "Actual Startup Time": 811.675, "Actual Total Time": 825.267, "Actual Rows": 128235, "Actual Loops": 1, "Sort Key": ["au.id"], "Sort Method": "external merge", "Sort Space Used": 6176, "Sort Space Type": "Disk", "Plans": [{"Node Type": "Hash Join", "Parent Relationship": "Outer", "Parallel Aware": false, "Async Capable": false, "Join Type": "Inner", "Startup Cost": 173086.33, "Total Cost": 422021.74, "Plan Rows": 34113, "Plan Width": 36, "Actual Startup Time": 149.099, "Actual Total Time": 760.675, "Actual Rows": 128235, "Actual Loops": 1, "Inner Unique": true, "Hash Cond": "(au.id = forum_hasmember_person.personid)", "Plans": [{"Node Type": "Hash Join", "Parent Relationship": "Outer", "Parallel Aware": false, "Async Capable": false, "Join Type": "Right", "Startup Cost": 3285.83, "Total Cost": 251650.31, "Plan Rows": 72925, "Plan Width": 36, "Actual Startup Time": 109.744, "Actual Total Time": 676.15, "Actual Rows": 184204, "Actual Loops": 1, "Inner Unique": true, "Hash Cond": "(message.creatorpersonid = au.id)", "Plans": [{"Node Type": "Nested Loop", "Parent Relationship": "Outer", "Parallel Aware": false, "Async Capable": false, "Join Type": "Inner", "Startup Cost": 2.69, "Total Cost": 248175.73, "Plan Rows": 72925, "Plan Width": 16, "Actual Startup Time": 81.666, "Actual Total Time": 580.054, "Actual Rows": 126748, "Actual Loops": 1, "Inner Unique": false, "Plans": [{"Node Type": "Aggregate", "Strategy": "Hashed", "Partial Mode": "Simple", "Parent Relationship": "Outer", "Parallel Aware": false, "Async Capable": false, "Startup Cost": 2.25, "Total Cost": 3.25, "Plan Rows": 100, "Plan Width": 8, "Actual Startup Time": 81.617, "Actual Total Time": 81.709, "Actual Rows": 100, "Actual Loops": 1, "Group Key": ["top100_popular_forums_1.id"], "Planned Partitions": 0, "HashAgg Batches": 1, "Peak Memory Usage": 24, "Disk Usage": 0, "Plans": [{"Node Type": "CTE Scan", "Parent Relationship": "Outer", "Parallel Aware": false, "Async Capable": false, "CTE Name": "top100_popular_forums", "Alias": "top100_popular_forums_1", "Startup Cost": 0.0, "Total Cost": 2.0, "Plan Rows": 100, "Plan Width": 8, "Actual Startup Time": 81.463, "Actual Total Time": 81.542, "Actual Rows": 100, "Actual Loops": 1}]}, {"Node Type": "Index Scan", "Parent Relationship": "Inner", "Parallel Aware": false, "Async Capable": false, "Scan Direction": "Forward", "Index Name": "message_containerforumid_idx", "Relation Name": "message", "Alias": "message", "Startup Cost": 0.44, "Total Cost": 2474.43, "Plan Rows": 729, "Plan Width": 24, "Actual Startup Time": 0.025, "Actual Total Time": 4.713, "Actual Rows": 1267, "Actual Loops": 100, "Index Cond": "(containerforumid = top100_popular_forums_1.id)", "Rows Removed by Index Recheck": 0}]}, {"Node Type": "Hash", "Parent Relationship": "Inner", "Parallel Aware": false, "Async Capable": false, "Startup Cost": 2424.73, "Total Cost": 2424.73, "Plan Rows": 68673, "Plan Width": 28, "Actual Startup Time": 27.884, "Actual Total Time": 27.885, "Actual Rows": 68673, "Actual Loops": 1, "Hash Buckets": 131072, "Original Hash Buckets": 131072, "Hash Batches": 1, "Original Hash Batches": 1, "Peak Memory Usage": 5374, "Plans": [{"Node Type": "Seq Scan", "Parent Relationship": "Outer", "Parallel Aware": false, "Async Capable": false, "Relation Name": "person", "Alias": "au", "Startup Cost": 0.0, "Total Cost": 2424.73, "Plan Rows": 68673, "Plan Width": 28, "Actual Startup Time": 0.025, "Actual Total Time": 14.552, "Actual Rows": 68673, "Actual Loops": 1}]}]}, {"Node Type": "Hash", "Parent Relationship": "Inner", "Parallel Aware": false, "Async Capable": false, "Startup Cost": 169398.95, "Total Cost": 169398.95, "Plan Rows": 32124, "Plan Width": 8, "Actual Startup Time": 39.277, "Actual Total Time": 39.279, "Actual Rows": 13215, "Actual Loops": 1, "Hash Buckets": 32768, "Original Hash Buckets": 32768, "Hash Batches": 1, "Original Hash Batches": 1, "Peak Memory Usage": 773, "Plans": [{"Node Type": "Aggregate", "Strategy": "Hashed", "Partial Mode": "Simple", "Parent Relationship": "Outer", "Parallel Aware": false, "Async Capable": false, "Startup Cost": 169077.71, "Total Cost": 169398.95, "Plan Rows": 32124, "Plan Width": 8, "Actual Startup Time": 35.189, "Actual Total Time": 37.158, "Actual Rows": 13215, "Actual Loops": 1, "Group Key": ["forum_hasmember_person.personid"], "Planned Partitions": 0, "HashAgg Batches": 1, "Peak Memory Usage": 2321, "Disk Usage": 0, "Plans": [{"Node Type": "Nested Loop", "Parent Relationship": "Outer", "Parallel Aware": false, "Async Capable": false, "Join Type": "Inner", "Startup Cost": 8.21, "Total Cost": 168955.94, "Plan Rows": 48707, "Plan Width": 8, "Actual Startup Time": 0.065, "Actual Total Time": 22.531, "Actual Rows": 70948, "Actual Loops": 1, "Inner Unique": false, "Plans": [{"Node Type": "CTE Scan", "Parent Relationship": "Outer", "Parallel Aware": false, "Async Capable": false, "CTE Name": "top100_popular_forums", "Alias": "top100_popular_forums", "Startup Cost": 0.0, "Total Cost": 2.0, "Plan Rows": 100, "Plan Width": 8, "Actual Startup Time": 0.001, "Actual Total Time": 0.027, "Actual Rows": 100, "Actual Loops": 1}, {"Node Type": "Bitmap Heap Scan", "Parent Relationship": "Inner", "Parallel Aware": false, "Async Capable": false, "Relation Name": "forum_hasmember_person", "Alias": "forum_hasmember_person", "Startup Cost": 8.21, "Total Cost": 1684.67, "Plan Rows": 487, "Plan Width": 16, "Actual Startup Time": 0.049, "Actual Total Time": 0.154, "Actual Rows": 709, "Actual Loops": 100, "Recheck Cond": "(forumid = top100_popular_forums.id)", "Rows Removed by Index Recheck": 0, "Exact Heap Blocks": 551, "Lossy Heap Blocks": 0, "Plans": [{"Node Type": "Bitmap Index Scan", "Parent Relationship": "Outer", "Parallel Aware": false, "Async Capable": false, "Index Name": "forum_hasmember_person_forumid_idx", "Startup Cost": 0.0, "Total Cost": 8.09, "Plan Rows": 487, "Plan Width": 0, "Actual Startup Time": 0.034, "Actual Total Time": 0.034, "Actual Rows": 709, "Actual Loops": 100, "Index Cond": "(forumid = top100_popular_forums.id)"}]}]}]}]}]}]}]}]}]}, "Planning Time": 0.613, "Triggers": [], "JIT": {"Functions": 47, "Options": {"Inlining": false, "Optimization": false, "Expressions": true, "Deforming": true}, "Timing": {"Generation": 3.151, "Inlining": 0.0, "Optimization": 1.551, "Emission": 27.601, "Total": 32.302}}, "Execution Time": 870.829}]